explorify/__init__.py
explorify/__main__.py
explorify/container.py
explorify/eda/__init__.py
explorify/eda/base.py
explorify/eda/bivariate/__init__.py
explorify/eda/bivariate/base.py
explorify/eda/bivariate/categorical.py
explorify/eda/bivariate/mixed.py
explorify/eda/bivariate/numeric.py
explorify/eda/data_prep/__init__.py
explorify/eda/data_prep/base.py
explorify/eda/data_prep/encode.py
explorify/eda/data_prep/outliers.py
explorify/eda/multivariate/__init__.py
explorify/eda/multivariate/analysis.py
explorify/eda/multivariate/base.py
explorify/eda/multivariate/cluster.py
explorify/eda/multivariate/dimension.py
explorify/eda/overview.py
explorify/eda/regression/__init__.py
explorify/eda/regression/base.py
explorify/eda/regression/simple.py
explorify/eda/stats/__init__.py
explorify/eda/stats/descriptive/__init__.py
explorify/eda/stats/descriptive/base.py
explorify/eda/stats/descriptive/categorical.py
explorify/eda/stats/descriptive/continuous.py
explorify/eda/stats/descriptive/summary.py
explorify/eda/stats/distribution/__init__.py
explorify/eda/stats/distribution/generate.py
explorify/eda/stats/inferential/__init__.py
explorify/eda/stats/inferential/association.py
explorify/eda/stats/inferential/base.py
explorify/eda/stats/inferential/centrality.py
explorify/eda/stats/inferential/correlation.py
explorify/eda/stats/inferential/gof.py
explorify/eda/stats/inferential/independence.py
explorify/eda/stats/inferential/profile.py
explorify/eda/stats/inferential/rank.py
explorify/eda/stats/inferential/variance.py
explorify/eda/univariate/__init__.py
explorify/eda/univariate/base.py
explorify/eda/univariate/categorical.py
explorify/eda/univariate/numeric.py
explorify/eda/visualize/__init__.py
explorify/eda/visualize/base.py
explorify/eda/visualize/visualizer.py
explorify/py.typed
explorify/utils/io.py
explorify/utils/print.py
explorify/utils/string.py
explorify-0.1.6.dist-info/WHEEL
explorify-0.1.6.dist-info/METADATA
explorify-0.1.6.dist-info/RECORD
