Metadata-Version: 2.1
Name: explorify
Version: 0.1.6
Summary: Explorify: Your modular solution for comprehensive data exploration. Dive deep with a suite of statistical techniques, tests, and visualizations designed for flexibility and ease of use.
Home-page: https://variancexplained.github.io/explorify
License: MIT
Author: John James
Author-email: john@variancexplained.com
Requires-Python: >=3.8.1,<4.0
Classifier: Development Status :: 4 - Beta
Classifier: Intended Audience :: Developers
Classifier: License :: OSI Approved :: MIT License
Classifier: Operating System :: OS Independent
Classifier: Programming Language :: Python
Classifier: Programming Language :: Python :: 3
Classifier: Programming Language :: Python :: 3.10
Classifier: Programming Language :: Python :: 3.11
Classifier: Programming Language :: Python :: 3.12
Classifier: Programming Language :: Python :: 3.8
Classifier: Programming Language :: Python :: 3.9
Classifier: Topic :: Software Development :: Libraries :: Python Modules
Classifier: Typing :: Typed
Requires-Dist: mkdocs-material
Requires-Dist: mkdocstrings[python] (>=0.23)
Requires-Dist: mypy
Requires-Dist: pre-commit
Requires-Dist: pymdown-extensions
Requires-Dist: pytest
Requires-Dist: pytest-cov
Requires-Dist: pytest-github-actions-annotate-failures
Requires-Dist: python-kacl
Requires-Dist: ruff (>=0.2.0)
Project-URL: Documentation, https://variancexplained.github.io/explorify
Project-URL: Repository, https://github.com/variancexplained/explorify
